h2j/__init__.py
h2j/core.py
h2j-0.1.2.dist-info/licenses/LICENSE
h2j-0.1.2.dist-info/METADATA
h2j-0.1.2.dist-info/WHEEL
h2j-0.1.2.dist-info/top_level.txt
h2j-0.1.2.dist-info/RECORD
