Metadata-Version: 2.4
Name: h2j
Version: 0.1.2
Summary: Convert HTML to JSON with clean keys and CSS-like classes
Home-page: https://github.com/SimBeSim/h2j
Author: Maxim Sergeyevich Shubin and Chatty Shubin
License: MIT
Classifier: Programming Language :: Python :: 3
Classifier: License :: OSI Approved :: MIT License
Classifier: Operating System :: OS Independent
Requires-Python: >=3.7
License-File: LICENSE
Requires-Dist: beautifulsoup4>=4.9
Dynamic: license-file
